<map>
  <entry>
    <string>teatro</string>
    <br.ufc.sma.Preferencia>
      <tipo>teatro</tipo>
      <preco>80.0</preco>
      <dataDeInicio>
        <time>1392185707406</time>
        <timezone>America/Cayenne</timezone>
      </dataDeInicio>
      <dataDeFim>
        <time>1392704107406</time>
        <timezone>America/Cayenne</timezone>
      </dataDeFim>
    </br.ufc.sma.Preferencia>
  </entry>
  <entry>
    <string>eletronico</string>
    <br.ufc.sma.Preferencia>
      <tipo>show</tipo>
      <preco>100.0</preco>
      <dataDeInicio>
        <time>1416636907406</time>
        <timezone>America/Cayenne</timezone>
      </dataDeInicio>
      <dataDeFim>
        <time>1418192107406</time>
        <timezone>America/Cayenne</timezone>
      </dataDeFim>
    </br.ufc.sma.Preferencia>
  </entry>
  <entry>
    <string>show</string>
    <br.ufc.sma.Preferencia reference="../../entry[2]/br.ufc.sma.Preferencia"/>
  </entry>
</map>
